anytraverse/__init__.py
anytraverse/helpers/__init__.py
anytraverse/helpers/device.py
anytraverse/utils/__init__.py
anytraverse/utils/_typing.py
anytraverse/utils/roi.py
anytraverse/utils/state.py
anytraverse/utils/trav_pref.py
anytraverse/utils/base/__init__.py
anytraverse/utils/base/attention_mapping.py
anytraverse/utils/base/encoding.py
anytraverse/utils/base/history.py
anytraverse/utils/base/map_pooling.py
anytraverse/utils/models/__init__.py
anytraverse/utils/models/clip.py
anytraverse/utils/models/clipseg.py
anytraverse/utils/models/nomic.py
anytraverse/utils/modules/__init__.py
anytraverse/utils/modules/trav_pooling.py
anytraverse/utils/modules/unc_pooling.py
anytraverse/utils/pipelines/__init__.py
anytraverse/utils/pipelines/base.py
anytraverse/utils/pipelines/paper.py
anytraverse-1.0.7.dist-info/METADATA
anytraverse-1.0.7.dist-info/WHEEL
anytraverse-1.0.7.dist-info/entry_points.txt
anytraverse-1.0.7.dist-info/licenses/LICENSE
anytraverse-1.0.7.dist-info/RECORD
