Metadata-Version: 2.4
Name: anytraverse
Version: 1.0.7
Summary: Offroad Traversability Segmentation with VLM and Human in the Loop
Author-email: Sattwik Kumar Sahu <sattwik21@iiserb.ac.in>, Agamdeep Singh <agamdeep20@iiserb.ac.in>, Karthik Babu Nambiar <karthik23@iiserb.ac.in>, Sujit P B <sujit@iiserb.ac.in>
License-File: LICENSE
Requires-Python: >=3.12
Requires-Dist: numpy>=1.26.4
Requires-Dist: pillow>=11.2.1
Requires-Dist: torch>=2.7.0
